dynabuffers/Dynabuffers.py
dynabuffers/DynabuffersEngine.py
dynabuffers/DynabuffersVisitor.py
dynabuffers/NamespaceResolver.py
dynabuffers/Registry.py
dynabuffers/TypeValidator.py
dynabuffers/__init__.py
dynabuffers/antlr/Dynabuffers.tokens
dynabuffers/antlr/DynabuffersLexer.py
dynabuffers/antlr/DynabuffersLexer.tokens
dynabuffers/antlr/DynabuffersListener.py
dynabuffers/antlr/DynabuffersParser.py
dynabuffers/antlr/DynabuffersVisitor.py
dynabuffers/api/IAnnotation.py
dynabuffers/api/ISerializable.py
dynabuffers/api/Subbyte.py
dynabuffers/api/__init__.py
dynabuffers/api/map/DynabuffersMap.py
dynabuffers/api/map/ImplicitDynabuffersMap.py
dynabuffers/ast/ClassType.py
dynabuffers/ast/EnumType.py
dynabuffers/ast/FieldType.py
dynabuffers/ast/NamespaceType.py
dynabuffers/ast/UnionType.py
dynabuffers/ast/__init__.py
dynabuffers/ast/annotation/GreaterEquals.py
dynabuffers/ast/annotation/GreaterThan.py
dynabuffers/ast/annotation/LowerEquals.py
dynabuffers/ast/annotation/LowerThan.py
dynabuffers/ast/annotation/MaxLength.py
dynabuffers/ast/annotation/MinLength.py
dynabuffers/ast/annotation/NotBlank.py
dynabuffers/ast/datatype/ArrayType.py
dynabuffers/ast/datatype/BooleanType.py
dynabuffers/ast/datatype/ByteType.py
dynabuffers/ast/datatype/FloatType.py
dynabuffers/ast/datatype/IntType.py
dynabuffers/ast/datatype/LongType.py
dynabuffers/ast/datatype/MapType.py
dynabuffers/ast/datatype/NoneType.py
dynabuffers/ast/datatype/OptionType.py
dynabuffers/ast/datatype/RefType.py
dynabuffers/ast/datatype/ShortType.py
dynabuffers/ast/datatype/StringType.py
dynabuffers/ast/datatype/__init__.py
dynabuffers/ast/structural/Annotation.py
dynabuffers/ast/structural/ClassOptions.py
dynabuffers/ast/structural/FieldOptions.py
dynabuffers/ast/structural/UnionOptions.py
dynabuffers/ast/structural/Value.py
dynabuffers/header/DynabuffersVersion.py
dynabuffers/header/Header.py
dynabuffers/header/RootElement.py
dynabuffers/header/__init__.py
dynabuffers-2.6.1.dist-info/entry_points.txt
dynabuffers-2.6.1.dist-info/WHEEL
dynabuffers-2.6.1.dist-info/METADATA
dynabuffers-2.6.1.dist-info/RECORD
