Metadata-Version: 2.1
Name: dynabuffers
Version: 2.6.1
Summary: Dynamic cross platform serialization library.
Author: Leftshift One
Author-email: contact@leftshift.one
Requires-Python: >3.5.0,<4.0.0
Classifier: Programming Language :: Python :: 3
Classifier: Programming Language :: Python :: 3.6
Classifier: Programming Language :: Python :: 3.7
Classifier: Programming Language :: Python :: 3.8
Requires-Dist: antlr4-python3-runtime (==4.7)
